README.md
payslip.py
setup.cfg
setup.py
ukpf.egg-info/PKG-INFO
ukpf.egg-info/SOURCES.txt
ukpf.egg-info/dependency_links.txt
ukpf.egg-info/top_level.txt