Metadata-Version: 2.1
Name: ukpf
Version: 0.1
Summary: A personal finance package for the UK tax system
Home-page: https://github.com/williamholtam/ukpersonalfinance
Author: William Holtam
Author-email: william.holtam@gmail.com
License: UNKNOWN
Download-URL: https://github.com/WilliamHoltam/ukpf/archive/v_01.tar.gz
Keywords: PERSONAL,FINANCE,UK,PAYSLIP
Platform: UNKNOWN
Classifier: Development Status :: 3 - Alpha
Classifier: Programming Language :: Python :: 3
Classifier: License :: OSI Approved :: GNU General Public License v3 or later (GPLv3+)
Classifier: Operating System :: OS Independent
